ntphy/__init__.py
ntphy/apps/jellyseer/receive.py
ntphy/utils/__init__.py
ntphy/utils/calculate.py
ntphy/utils/messages.py
ntphy/utils/output.py
ntphy/utils/server.py
ntphy-0.0.0.1.dist-info/METADATA
ntphy-0.0.0.1.dist-info/WHEEL
ntphy-0.0.0.1.dist-info/top_level.txt
ntphy-0.0.0.1.dist-info/RECORD
