Metadata-Version: 2.1
Name: ntphy
Version: 0.0.0.1
Summary: A custom ntfy.sh client catered for various applications
Author: Mike Afshari
Author-email: theneed4swede@gmail.com
License: MIT
Classifier: Programming Language :: Python :: 3
Classifier: License :: OSI Approved :: MIT License
Classifier: Operating System :: OS Independent
Requires-Python: >=3.6
Requires-Dist: certifi (==2024.2.2)
Requires-Dist: charset-normalizer (==3.3.2)
Requires-Dist: idna (==3.7)
Requires-Dist: requests (==2.31.0)
Requires-Dist: urllib3 (==2.2.1)
